thestage_license/__init__.py
thestage_license/pyarmor_runtime_008031/__init__.py
thestage_license/pyarmor_runtime_008031/py312/pyarmor_runtime.so
thestage_license-1.0.0.dist-info/METADATA
thestage_license-1.0.0.dist-info/WHEEL
thestage_license-1.0.0.dist-info/top_level.txt
thestage_license-1.0.0.dist-info/RECORD
